Metadata-Version: 2.1
Name: parsed
Version: 0.1
Summary: A simple, pure Python 2.7/3.x HTTP parser
Home-page: https://github.com/nggit/parsed
Author: nggit
Author-email: contact@anggit.com
License: MIT
Platform: UNKNOWN
Classifier: Development Status :: 5 - Production/Stable
Classifier: License :: OSI Approved :: MIT License
Classifier: Operating System :: OS Independent
